DiveIntoPythonZhongwenban/README.md
DiveIntoPythonZhongwenban/__init__.py
DiveIntoPythonZhongwenban/__main__.py
DiveIntoPythonZhongwenban/file.epub
DiveIntoPythonZhongwenban/index.html
DiveIntoPythonZhongwenban/css/__init__.py
DiveIntoPythonZhongwenban/css/annotations.css
DiveIntoPythonZhongwenban/css/main.css
DiveIntoPythonZhongwenban/css/normalize.css
DiveIntoPythonZhongwenban/css/popup.css
DiveIntoPythonZhongwenban/font/__init__.py
DiveIntoPythonZhongwenban/font/fontello.eot
DiveIntoPythonZhongwenban/font/fontello.svg
DiveIntoPythonZhongwenban/font/fontello.ttf
DiveIntoPythonZhongwenban/font/fontello.woff
DiveIntoPythonZhongwenban/img/__init__.py
DiveIntoPythonZhongwenban/img/annotator-glyph-sprite.png
DiveIntoPythonZhongwenban/img/annotator-icon-sprite.png
DiveIntoPythonZhongwenban/img/apple-touch-icon.png
DiveIntoPythonZhongwenban/img/cancelfullscreen.png
DiveIntoPythonZhongwenban/img/close.png
DiveIntoPythonZhongwenban/img/fullscreen.png
DiveIntoPythonZhongwenban/img/loader.gif
DiveIntoPythonZhongwenban/img/menu-icon.png
DiveIntoPythonZhongwenban/img/save.png
DiveIntoPythonZhongwenban/img/saved.png
DiveIntoPythonZhongwenban/img/settings-s.png
DiveIntoPythonZhongwenban/img/settings.png
DiveIntoPythonZhongwenban/img/star.png
DiveIntoPythonZhongwenban/js/__init__.py
DiveIntoPythonZhongwenban/js/epub.js
DiveIntoPythonZhongwenban/js/epub.min.js
DiveIntoPythonZhongwenban/js/epub.min.map
DiveIntoPythonZhongwenban/js/hooks.min.js
DiveIntoPythonZhongwenban/js/hooks.min.map
DiveIntoPythonZhongwenban/js/reader.js
DiveIntoPythonZhongwenban/js/reader.js.map
DiveIntoPythonZhongwenban/js/reader.min.js
DiveIntoPythonZhongwenban/js/reader.min.map
DiveIntoPythonZhongwenban/js/hooks/__init__.py
DiveIntoPythonZhongwenban/js/hooks/extensions/__init__.py
DiveIntoPythonZhongwenban/js/hooks/extensions/highlight.js
DiveIntoPythonZhongwenban/js/libs/__init__.py
DiveIntoPythonZhongwenban/js/libs/jquery.min.js
DiveIntoPythonZhongwenban/js/libs/localforage.min.js
dive_into_python_zhongwenban-2024.3.1.0.dist-info/METADATA
dive_into_python_zhongwenban-2024.3.1.0.dist-info/WHEEL
dive_into_python_zhongwenban-2024.3.1.0.dist-info/entry_points.txt
dive_into_python_zhongwenban-2024.3.1.0.dist-info/top_level.txt
dive_into_python_zhongwenban-2024.3.1.0.dist-info/RECORD
